mn2/__init__.py
mn2/models.py
mn2/structures.py
mn2/variances.py
mn2/data/evt12.csv
mn2/data/oats.csv
mn2/sample/oats.py
mn2-0.0.15.dist-info/LICENSE
mn2-0.0.15.dist-info/METADATA
mn2-0.0.15.dist-info/WHEEL
mn2-0.0.15.dist-info/top_level.txt
mn2-0.0.15.dist-info/RECORD
